xy_health_measurement_sdk_configuration/Utility.py
xy_health_measurement_sdk_configuration/__init__.py
xy_health_measurement_sdk_configuration/protos/Category_pb2.py
xy_health_measurement_sdk_configuration/protos/Chunk_pb2.py
xy_health_measurement_sdk_configuration/protos/Report_pb2.py
xy_health_measurement_sdk_configuration/protos/Validation_pb2.py
xy_health_measurement_sdk_configuration/protos/__init__.py
xy_health_measurement_sdk_configuration/resources/__init__.py
xy_health_measurement_sdk_configuration/resources/config.json
xy_health_measurement_sdk_configuration-1.0.3.dist-info/METADATA
xy_health_measurement_sdk_configuration-1.0.3.dist-info/WHEEL
xy_health_measurement_sdk_configuration-1.0.3.dist-info/top_level.txt
xy_health_measurement_sdk_configuration-1.0.3.dist-info/RECORD
