Metadata-Version: 2.4
Name: xy_health_measurement_sdk_configuration
Version: 1.0.3
Summary: 小阳心健康测量SDK配置
Author-email: Colin Chang <zhangcheng@xymind.cn>
Keywords: 健康测量,生理测量,情绪测量,健康风险,小阳科技
Classifier: Programming Language :: Python :: 3.8
Classifier: Programming Language :: Python :: 3.9
Classifier: Programming Language :: Python :: 3.10
Classifier: Programming Language :: Python :: 3.11
Classifier: License :: OSI Approved :: MIT License
Classifier: Operating System :: OS Independent
Requires-Python: <=3.11,>=3.8
Requires-Dist: protobuf==3.19.6
